klout_to_graphite
