Metadata-Version: 1.0
Name: klout-to-graphite
Version: 0.0.3
Summary: A tool to send Klout scores to Graphite
Home-page: https://github.com/philipcristiano/klout-to-graphite
Author: Philip Cristiano
Author-email: philipcristiano@gmail.com
License: BSD
Keywords: klout graphite
Platform: UNKNOWN
